red/__init__.py
red/cli/__init__.py
red/cli/__main__.py
red/cli/main.py
red_reddit_cli-0.2.1.dist-info/WHEEL
red_reddit_cli-0.2.1.dist-info/entry_points.txt
red_reddit_cli-0.2.1.dist-info/METADATA
red_reddit_cli-0.2.1.dist-info/RECORD
