Metadata-Version: 2.3
Name: red-reddit-cli
Version: 0.2.1
Summary: Red - a Reddit CLI
Requires-Dist: click-aliases>=1.0.5
Requires-Dist: praw>=7.8.1
Requires-Dist: pyyaml>=6.0.3
Requires-Dist: rich>=14.2.0
Requires-Dist: typer>=0.21.0
Requires-Dist: xdg-base-dirs>=6.0.2
Requires-Python: >=3.13
